argunizer/__init__.py
argunizer/shaker.py
argunizer-0.1.4.data/scripts/argunize-clean.py
argunizer-0.1.4.data/scripts/argunize-copy.py
argunizer-0.1.4.data/scripts/argunize-move.py
argunizer-0.1.4.data/scripts/argunize-symlink.py
argunizer-0.1.4.dist-info/LICENSE
argunizer-0.1.4.dist-info/METADATA
argunizer-0.1.4.dist-info/WHEEL
argunizer-0.1.4.dist-info/top_level.txt
argunizer-0.1.4.dist-info/RECORD
