Metadata-Version: 2.1
Name: argunizer
Version: 0.1.4
Summary: Argunizer is a tool for creating and maintaining temporal hierarchies.
Home-page: https://gitlab.com/svimes/argunizer
Author: Lari Huttunen
Author-email: mitcode@huttu.net
License: UNKNOWN
Platform: UNKNOWN
Classifier: Programming Language :: Python :: 3
Classifier: License :: OSI Approved :: MIT License
Classifier: Operating System :: OS Independent
Requires-Python: >=3.7
